salome/bin/HXX2SALOME_Test/compile_HXX2SALOME_GENERIC_CLASS_NAME.sh
salome/bin/HXX2SALOME_Test/env_HXX2SALOME.csh
salome/bin/HXX2SALOME_Test/env_HXX2SALOME.sh
salome/bin/HXX2SALOME_Test/hxx2salome
salome/bin/HXX2SALOME_Test/hxx2salome_check
salome/bin/HXX2SALOME_Test/hxx2salome_corba
salome/bin/HXX2SALOME_Test/hxx2salome_cpp
salome/bin/HXX2SALOME_Test/parse0.awk
salome/bin/HXX2SALOME_Test/parse01.awk
salome/bin/HXX2SALOME_Test/parse1.awk
salome/bin/HXX2SALOME_Test/parse2.awk
salome/bin/HXX2SALOME_Test/parse3.awk
salome/bin/HXX2SALOME_Test/parse30.awk
salome/bin/HXX2SALOME_Test/parse4.awk
salome/bin/HXX2SALOME_Test/parse5.awk
salome/bin/HXX2SALOME_Test/renameSalomeModule
salome/bin/HXX2SALOME_Test/runIDLparser
salome/bin/HXX2SALOME_Test/HXX2SALOME_GENERIC_CLASS_NAME_SRC/AUTHORS
salome/bin/HXX2SALOME_Test/HXX2SALOME_GENERIC_CLASS_NAME_SRC/COPYING
salome/bin/HXX2SALOME_Test/HXX2SALOME_GENERIC_CLASS_NAME_SRC/ChangeLog
salome/bin/HXX2SALOME_Test/HXX2SALOME_GENERIC_CLASS_NAME_SRC/INSTALL
salome/bin/HXX2SALOME_Test/HXX2SALOME_GENERIC_CLASS_NAME_SRC/Makefile.am
salome/bin/HXX2SALOME_Test/HXX2SALOME_GENERIC_CLASS_NAME_SRC/NEWS
salome/bin/HXX2SALOME_Test/HXX2SALOME_GENERIC_CLASS_NAME_SRC/README
salome/bin/HXX2SALOME_Test/HXX2SALOME_GENERIC_CLASS_NAME_SRC/build_configure
salome/bin/HXX2SALOME_Test/HXX2SALOME_GENERIC_CLASS_NAME_SRC/configure.in.base
salome/bin/HXX2SALOME_Test/HXX2SALOME_GENERIC_CLASS_NAME_SRC/py-compile
salome/bin/HXX2SALOME_Test/HXX2SALOME_GENERIC_CLASS_NAME_SRC/rfind
salome/bin/HXX2SALOME_Test/HXX2SALOME_GENERIC_CLASS_NAME_SRC/root_clean
salome/bin/HXX2SALOME_Test/HXX2SALOME_GENERIC_CLASS_NAME_SRC/adm_local/Makefile.am
salome/bin/HXX2SALOME_Test/HXX2SALOME_GENERIC_CLASS_NAME_SRC/adm_local/unix/Makefile.am
salome/bin/HXX2SALOME_Test/HXX2SALOME_GENERIC_CLASS_NAME_SRC/adm_local/unix/SALOMEconfig.h.in
salome/bin/HXX2SALOME_Test/HXX2SALOME_GENERIC_CLASS_NAME_SRC/adm_local/unix/make_begin.am
salome_yacs-9.14.0.post7.dist-info/METADATA
salome_yacs-9.14.0.post7.dist-info/WHEEL
salome_yacs-9.14.0.post7.dist-info/entry_points.txt
salome_yacs-9.14.0.post7.dist-info/RECORD
salome_yacs-9.14.0.post7.dist-info/sboms/auditwheel.cdx.json
